{"Thresh":{"id":412,"key":"Thresh","name":"Thresh","title":"the Chain Warden","stats":{"total":{"samples":{"normal":18528,"urf":2721},"wins":{"normal":9072,"urf":1125}},"ad":{"samples":{"normal":329,"urf":832},"wins":{"normal":117,"urf":353}},"ap":{"samples":{"normal":56,"urf":796},"wins":{"normal":21,"urf":329}},"fighter":{"samples":{"normal":18,"urf":35},"wins":{"normal":7,"urf":16}},"tank":{"samples":{"normal":627,"urf":756},"wins":{"normal":281,"urf":308}},"support":{"samples":{"normal":17498,"urf":302},"wins":{"normal":8646,"urf":119}}}},"Aatrox":{"id":266,"key":"Aatrox","name":"Aatrox","title":"the Darkin Blade","stats":{"total":{"samples":{"normal":1441,"urf":990},"wins":{"normal":705,"urf":494}},"ad":{"samples":{"normal":182,"urf":190},"wins":{"normal":81,"urf":106}},"ap":{"samples":{"normal":3,"urf":52},"wins":{"normal":1,"urf":22}},"fighter":{"samples":{"normal":661,"urf":615},"wins":{"normal":374,"urf":304}},"tank":{"samples":{"normal":581,"urf":133},"wins":{"normal":244,"urf":62}},"support":{"samples":{"normal":14,"urf":0},"wins":{"normal":5,"urf":0}}}},"Tryndamere":{"id":23,"key":"Tryndamere","name":"Tryndamere","title":"the Barbarian King","stats":{"total":{"samples":{"normal":3376,"urf":3900},"wins":{"normal":1745,"urf":2073}},"ad":{"samples":{"normal":3038,"urf":2309},"wins":{"normal":1600,"urf":1265}},"ap":{"samples":{"normal":63,"urf":1439},"wins":{"normal":30,"urf":740}},"fighter":{"samples":{"normal":220,"urf":112},"wins":{"normal":98,"urf":51}},"tank":{"samples":{"normal":45,"urf":39},"wins":{"normal":15,"urf":16}},"support":{"samples":{"normal":10,"urf":1},"wins":{"normal":2,"urf":1}}}},"Gragas":{"id":79,"key":"Gragas","name":"Gragas","title":"the Rabble Rouser","stats":{"total":{"samples":{"normal":5876,"urf":2143},"wins":{"normal":3018,"urf":977}},"ad":{"samples":{"normal":5,"urf":11},"wins":{"normal":3,"urf":3}},"ap":{"samples":{"normal":1434,"urf":1949},"wins":{"normal":675,"urf":894}},"fighter":{"samples":{"normal":2,"urf":2},"wins":{"normal":0,"urf":1}},"tank":{"samples":{"normal":4067,"urf":174},"wins":{"normal":2150,"urf":75}},"support":{"samples":{"normal":368,"urf":7},"wins":{"normal":190,"urf":4}}}},"Cassiopeia":{"id":69,"key":"Cassiopeia","name":"Cassiopeia","title":"the Serpent's Embrace","stats":{"total":{"samples":{"normal":2416,"urf":1426},"wins":{"normal":1186,"urf":674}},"ad":{"samples":{"normal":4,"urf":5},"wins":{"normal":2,"urf":1}},"ap":{"samples":{"normal":2388,"urf":1414},"wins":{"normal":1177,"urf":671}},"fighter":{"samples":{"normal":0,"urf":0},"wins":{"normal":0,"urf":0}},"tank":{"samples":{"normal":3,"urf":7},"wins":{"normal":1,"urf":2}},"support":{"samples":{"normal":21,"urf":0},"wins":{"normal":6,"urf":0}}}},"Poppy":{"id":78,"key":"Poppy","name":"Poppy","title":"the Iron Ambassador","stats":{"total":{"samples":{"normal":942,"urf":3723},"wins":{"normal":505,"urf":2063}},"ad":{"samples":{"normal":114,"urf":844},"wins":{"normal":72,"urf":521}},"ap":{"samples":{"normal":33,"urf":657},"wins":{"normal":15,"urf":349}},"fighter":{"samples":{"normal":180,"urf":1072},"wins":{"normal":93,"urf":597}},"tank":{"samples":{"normal":579,"urf":1144},"wins":{"normal":307,"urf":594}},"support":{"samples":{"normal":36,"urf":6},"wins":{"normal":18,"urf":2}}}},"Ryze":{"id":13,"key":"Ryze","name":"Ryze","title":"the Rogue Mage","stats":{"total":{"samples":{"normal":1901,"urf":4636},"wins":{"normal":884,"urf":2174}},"ad":{"samples":{"normal":5,"urf":18},"wins":{"normal":2,"urf":10}},"ap":{"samples":{"normal":1522,"urf":3963},"wins":{"normal":697,"urf":1869}},"fighter":{"samples":{"normal":2,"urf":1},"wins":{"normal":0,"urf":1}},"tank":{"samples":{"normal":307,"urf":613},"wins":{"normal":166,"urf":274}},"support":{"samples":{"normal":65,"urf":41},"wins":{"normal":19,"urf":20}}}},"Sion":{"id":14,"key":"Sion","name":"Sion","title":"The Undead Juggernaut","stats":{"total":{"samples":{"normal":6644,"urf":2310},"wins":{"normal":3527,"urf":1025}},"ad":{"samples":{"normal":30,"urf":162},"wins":{"normal":17,"urf":78}},"ap":{"samples":{"normal":53,"urf":268},"wins":{"normal":37,"urf":110}},"fighter":{"samples":{"normal":653,"urf":854},"wins":{"normal":352,"urf":389}},"tank":{"samples":{"normal":5429,"urf":1010},"wins":{"normal":2878,"urf":439}},"support":{"samples":{"normal":479,"urf":16},"wins":{"normal":243,"urf":9}}}},"Annie":{"id":1,"key":"Annie","name":"Annie","title":"the Dark Child","stats":{"total":{"samples":{"normal":10357,"urf":6934},"wins":{"normal":5324,"urf":3487}},"ad":{"samples":{"normal":24,"urf":29},"wins":{"normal":8,"urf":12}},"ap":{"samples":{"normal":8510,"urf":6862},"wins":{"normal":4520,"urf":3453}},"fighter":{"samples":{"normal":1,"urf":2},"wins":{"normal":1,"urf":1}},"tank":{"samples":{"normal":18,"urf":31},"wins":{"normal":5,"urf":16}},"support":{"samples":{"normal":1804,"urf":10},"wins":{"normal":790,"urf":5}}}},"Karma":{"id":43,"key":"Karma","name":"Karma","title":"the Enlightened One","stats":{"total":{"samples":{"normal":2946,"urf":6341},"wins":{"normal":1399,"urf":2978}},"ad":{"samples":{"normal":6,"urf":23},"wins":{"normal":1,"urf":11}},"ap":{"samples":{"normal":2053,"urf":6257},"wins":{"normal":1016,"urf":2941}},"fighter":{"samples":{"normal":0,"urf":2},"wins":{"normal":0,"urf":1}},"tank":{"samples":{"normal":19,"urf":41},"wins":{"normal":5,"urf":18}},"support":{"samples":{"normal":868,"urf":18},"wins":{"normal":377,"urf":7}}}},"Nautilus":{"id":111,"key":"Nautilus","name":"Nautilus","title":"the Titan of the Depths","stats":{"total":{"samples":{"normal":7493,"urf":3439},"wins":{"normal":3870,"urf":1683}},"ad":{"samples":{"normal":13,"urf":34},"wins":{"normal":7,"urf":19}},"ap":{"samples":{"normal":302,"urf":1768},"wins":{"normal":135,"urf":884}},"fighter":{"samples":{"normal":9,"urf":36},"wins":{"normal":3,"urf":18}},"tank":{"samples":{"normal":3352,"urf":1529},"wins":{"normal":1742,"urf":735}},"support":{"samples":{"normal":3817,"urf":72},"wins":{"normal":1983,"urf":27}}}},"Lux":{"id":99,"key":"Lux","name":"Lux","title":"the Lady of Luminosity","stats":{"total":{"samples":{"normal":5016,"urf":13722},"wins":{"normal":2522,"urf":6438}},"ad":{"samples":{"normal":8,"urf":39},"wins":{"normal":1,"urf":23}},"ap":{"samples":{"normal":4697,"urf":13648},"wins":{"normal":2390,"urf":6400}},"fighter":{"samples":{"normal":1,"urf":1},"wins":{"normal":0,"urf":1}},"tank":{"samples":{"normal":6,"urf":30},"wins":{"normal":5,"urf":12}},"support":{"samples":{"normal":304,"urf":4},"wins":{"normal":126,"urf":2}}}},"Ahri":{"id":103,"key":"Ahri","name":"Ahri","title":"the Nine-Tailed Fox","stats":{"total":{"samples":{"normal":8201,"urf":9438},"wins":{"normal":4139,"urf":4919}},"ad":{"samples":{"normal":33,"urf":40},"wins":{"normal":16,"urf":22}},"ap":{"samples":{"normal":8127,"urf":9383},"wins":{"normal":4113,"urf":4890}},"fighter":{"samples":{"normal":1,"urf":3},"wins":{"normal":0,"urf":3}},"tank":{"samples":{"normal":16,"urf":7},"wins":{"normal":2,"urf":3}},"support":{"samples":{"normal":24,"urf":5},"wins":{"normal":8,"urf":1}}}},"Olaf":{"id":2,"key":"Olaf","name":"Olaf","title":"the Berserker","stats":{"total":{"samples":{"normal":1619,"urf":1286},"wins":{"normal":749,"urf":623}},"ad":{"samples":{"normal":35,"urf":182},"wins":{"normal":17,"urf":88}},"ap":{"samples":{"normal":2,"urf":1},"wins":{"normal":0,"urf":0}},"fighter":{"samples":{"normal":638,"urf":860},"wins":{"normal":295,"urf":442}},"tank":{"samples":{"normal":931,"urf":240},"wins":{"normal":434,"urf":92}},"support":{"samples":{"normal":13,"urf":3},"wins":{"normal":3,"urf":1}}}},"Viktor":{"id":112,"key":"Viktor","name":"Viktor","title":"the Machine Herald","stats":{"total":{"samples":{"normal":3278,"urf":1892},"wins":{"normal":1581,"urf":912}},"ad":{"samples":{"normal":3,"urf":3},"wins":{"normal":1,"urf":0}},"ap":{"samples":{"normal":3250,"urf":1876},"wins":{"normal":1570,"urf":906}},"fighter":{"samples":{"normal":1,"urf":1},"wins":{"normal":0,"urf":1}},"tank":{"samples":{"normal":4,"urf":10},"wins":{"normal":0,"urf":4}},"support":{"samples":{"normal":20,"urf":2},"wins":{"normal":10,"urf":1}}}},"Anivia":{"id":34,"key":"Anivia","name":"Anivia","title":"the Cryophoenix","stats":{"total":{"samples":{"normal":1549,"urf":2124},"wins":{"normal":750,"urf":932}},"ad":{"samples":{"normal":4,"urf":28},"wins":{"normal":0,"urf":7}},"ap":{"samples":{"normal":1498,"urf":2033},"wins":{"normal":738,"urf":899}},"fighter":{"samples":{"normal":1,"urf":1},"wins":{"normal":0,"urf":0}},"tank":{"samples":{"normal":3,"urf":48},"wins":{"normal":0,"urf":20}},"support":{"samples":{"normal":43,"urf":14},"wins":{"normal":12,"urf":6}}}},"Garen":{"id":86,"key":"Garen","name":"Garen","title":"The Might of Demacia","stats":{"total":{"samples":{"normal":4023,"urf":2713},"wins":{"normal":1997,"urf":1305}},"ad":{"samples":{"normal":412,"urf":1042},"wins":{"normal":243,"urf":526}},"ap":{"samples":{"normal":5,"urf":7},"wins":{"normal":1,"urf":3}},"fighter":{"samples":{"normal":762,"urf":469},"wins":{"normal":373,"urf":214}},"tank":{"samples":{"normal":2799,"urf":1179},"wins":{"normal":1366,"urf":556}},"support":{"samples":{"normal":45,"urf":16},"wins":{"normal":14,"urf":6}}}},"Singed":{"id":27,"key":"Singed","name":"Singed","title":"the Mad Chemist","stats":{"total":{"samples":{"normal":1755,"urf":2644},"wins":{"normal":821,"urf":1281}},"ad":{"samples":{"normal":1,"urf":10},"wins":{"normal":0,"urf":2}},"ap":{"samples":{"normal":1095,"urf":1655},"wins":{"normal":522,"urf":812}},"fighter":{"samples":{"normal":0,"urf":6},"wins":{"normal":0,"urf":0}},"tank":{"samples":{"normal":600,"urf":951},"wins":{"normal":278,"urf":453}},"support":{"samples":{"normal":59,"urf":22},"wins":{"normal":21,"urf":14}}}},"Lissandra":{"id":127,"key":"Lissandra","name":"Lissandra","title":"the Ice Witch","stats":{"total":{"samples":{"normal":3609,"urf":2083},"wins":{"normal":1664,"urf":981}},"ad":{"samples":{"normal":1,"urf":10},"wins":{"normal":1,"urf":7}},"ap":{"samples":{"normal":3581,"urf":2064},"wins":{"normal":1654,"urf":971}},"fighter":{"samples":{"normal":0,"urf":0},"wins":{"normal":0,"urf":0}},"tank":{"samples":{"normal":1,"urf":8},"wins":{"normal":0,"urf":3}},"support":{"samples":{"normal":26,"urf":1},"wins":{"normal":9,"urf":0}}}},"Maokai":{"id":57,"key":"Maokai","name":"Maokai","title":"the Twisted Treant","stats":{"total":{"samples":{"normal":4553,"urf":8761},"wins":{"normal":2263,"urf":4636}},"ad":{"samples":{"normal":5,"urf":27},"wins":{"normal":1,"urf":13}},"ap":{"samples":{"normal":627,"urf":5975},"wins":{"normal":241,"urf":3206}},"fighter":{"samples":{"normal":3,"urf":11},"wins":{"normal":1,"urf":7}},"tank":{"samples":{"normal":3487,"urf":2710},"wins":{"normal":1831,"urf":1392}},"support":{"samples":{"normal":431,"urf":38},"wins":{"normal":189,"urf":18}}}},"Morgana":{"id":25,"key":"Morgana","name":"Morgana","title":"Fallen Angel","stats":{"total":{"samples":{"normal":12022,"urf":11083},"wins":{"normal":6088,"urf":5496}},"ad":{"samples":{"normal":5,"urf":25},"wins":{"normal":1,"urf":11}},"ap":{"samples":{"normal":9483,"urf":11013},"wins":{"normal":5017,"urf":5467}},"fighter":{"samples":{"normal":3,"urf":1},"wins":{"normal":1,"urf":1}},"tank":{"samples":{"normal":40,"urf":33},"wins":{"normal":18,"urf":15}},"support":{"samples":{"normal":2491,"urf":11},"wins":{"normal":1051,"urf":2}}}},"Evelynn":{"id":28,"key":"Evelynn","name":"Evelynn","title":"the Widowmaker","stats":{"total":{"samples":{"normal":1916,"urf":10224},"wins":{"normal":924,"urf":5496}},"ad":{"samples":{"normal":44,"urf":413},"wins":{"normal":24,"urf":177}},"ap":{"samples":{"normal":383,"urf":8548},"wins":{"normal":192,"urf":4669}},"fighter":{"samples":{"normal":395,"urf":214},"wins":{"normal":161,"urf":124}},"tank":{"samples":{"normal":1041,"urf":1037},"wins":{"normal":531,"urf":522}},"support":{"samples":{"normal":53,"urf":12},"wins":{"normal":16,"urf":4}}}},"Fizz":{"id":105,"key":"Fizz","name":"Fizz","title":"the Tidal Trickster","stats":{"total":{"samples":{"normal":5362,"urf":10141},"wins":{"normal":2732,"urf":5559}},"ad":{"samples":{"normal":360,"urf":484},"wins":{"normal":158,"urf":275}},"ap":{"samples":{"normal":2498,"urf":9024},"wins":{"normal":1327,"urf":4936}},"fighter":{"samples":{"normal":148,"urf":148},"wins":{"normal":69,"urf":90}},"tank":{"samples":{"normal":2328,"urf":479},"wins":{"normal":1172,"urf":256}},"support":{"samples":{"normal":28,"urf":6},"wins":{"normal":6,"urf":2}}}},"Zed":{"id":238,"key":"Zed","name":"Zed","title":"the Master of Shadows","stats":{"total":{"samples":{"normal":11637,"urf":15780},"wins":{"normal":5687,"urf":8227}},"ad":{"samples":{"normal":2942,"urf":8668},"wins":{"normal":1523,"urf":4585}},"ap":{"samples":{"normal":11,"urf":32},"wins":{"normal":4,"urf":11}},"fighter":{"samples":{"normal":8582,"urf":7019},"wins":{"normal":4133,"urf":3607}},"tank":{"samples":{"normal":87,"urf":56},"wins":{"normal":27,"urf":23}},"support":{"samples":{"normal":15,"urf":5},"wins":{"normal":0,"urf":1}}}},"Heimerdinger":{"id":74,"key":"Heimerdinger","name":"Heimerdinger","title":"the Revered Inventor","stats":{"total":{"samples":{"normal":2590,"urf":3551},"wins":{"normal":1413,"urf":1720}},"ad":{"samples":{"normal":4,"urf":18},"wins":{"normal":2,"urf":4}},"ap":{"samples":{"normal":2548,"urf":3509},"wins":{"normal":1390,"urf":1704}},"fighter":{"samples":{"normal":1,"urf":3},"wins":{"normal":1,"urf":1}},"tank":{"samples":{"normal":6,"urf":16},"wins":{"normal":5,"urf":8}},"support":{"samples":{"normal":31,"urf":5},"wins":{"normal":15,"urf":3}}}},"Rumble":{"id":68,"key":"Rumble","name":"Rumble","title":"the Mechanized Menace","stats":{"total":{"samples":{"normal":2797,"urf":1766},"wins":{"normal":1372,"urf":944}},"ad":{"samples":{"normal":0,"urf":4},"wins":{"normal":0,"urf":1}},"ap":{"samples":{"normal":2740,"urf":1733},"wins":{"normal":1357,"urf":925}},"fighter":{"samples":{"normal":0,"urf":2},"wins":{"normal":0,"urf":0}},"tank":{"samples":{"normal":44,"urf":24},"wins":{"normal":10,"urf":17}},"support":{"samples":{"normal":13,"urf":3},"wins":{"normal":5,"urf":1}}}},"Mordekaiser":{"id":82,"key":"Mordekaiser","name":"Mordekaiser","title":"the Master of Metal","stats":{"total":{"samples":{"normal":1290,"urf":2881},"wins":{"normal":644,"urf":1451}},"ad":{"samples":{"normal":2,"urf":17},"wins":{"normal":1,"urf":7}},"ap":{"samples":{"normal":1190,"urf":2712},"wins":{"normal":607,"urf":1383}},"fighter":{"samples":{"normal":0,"urf":17},"wins":{"normal":0,"urf":5}},"tank":{"samples":{"normal":93,"urf":131},"wins":{"normal":35,"urf":55}},"support":{"samples":{"normal":5,"urf":4},"wins":{"normal":1,"urf":1}}}},"Sona":{"id":37,"key":"Sona","name":"Sona","title":"Maven of the Strings","stats":{"total":{"samples":{"normal":7436,"urf":8468},"wins":{"normal":3855,"urf":4710}},"ad":{"samples":{"normal":23,"urf":42},"wins":{"normal":9,"urf":27}},"ap":{"samples":{"normal":1928,"urf":8102},"wins":{"normal":1059,"urf":4515}},"fighter":{"samples":{"normal":2,"urf":3},"wins":{"normal":1,"urf":0}},"tank":{"samples":{"normal":93,"urf":110},"wins":{"normal":54,"urf":52}},"support":{"samples":{"normal":5390,"urf":211},"wins":{"normal":2732,"urf":116}}}},"Katarina":{"id":55,"key":"Katarina","name":"Katarina","title":"the Sinister Blade","stats":{"total":{"samples":{"normal":7709,"urf":11594},"wins":{"normal":4087,"urf":5771}},"ad":{"samples":{"normal":9,"urf":57},"wins":{"normal":6,"urf":28}},"ap":{"samples":{"normal":7644,"urf":11475},"wins":{"normal":4063,"urf":5712}},"fighter":{"samples":{"normal":17,"urf":19},"wins":{"normal":5,"urf":11}},"tank":{"samples":{"normal":21,"urf":39},"wins":{"normal":8,"urf":19}},"support":{"samples":{"normal":18,"urf":4},"wins":{"normal":5,"urf":1}}}},"KogMaw":{"id":96,"key":"KogMaw","name":"Kog'Maw","title":"the Mouth of the Abyss","stats":{"total":{"samples":{"normal":2795,"urf":3494},"wins":{"normal":1388,"urf":1699}},"ad":{"samples":{"normal":1571,"urf":529},"wins":{"normal":800,"urf":243}},"ap":{"samples":{"normal":436,"urf":2891},"wins":{"normal":230,"urf":1429}},"fighter":{"samples":{"normal":2,"urf":7},"wins":{"normal":1,"urf":0}},"tank":{"samples":{"normal":781,"urf":66},"wins":{"normal":356,"urf":27}},"support":{"samples":{"normal":5,"urf":1},"wins":{"normal":1,"urf":0}}}},"Ashe":{"id":22,"key":"Ashe","name":"Ashe","title":"the Frost Archer","stats":{"total":{"samples":{"normal":5510,"urf":10119},"wins":{"normal":2840,"urf":4751}},"ad":{"samples":{"normal":5328,"urf":8188},"wins":{"normal":2768,"urf":3906}},"ap":{"samples":{"normal":30,"urf":1828},"wins":{"normal":8,"urf":798}},"fighter":{"samples":{"normal":39,"urf":56},"wins":{"normal":12,"urf":25}},"tank":{"samples":{"normal":27,"urf":42},"wins":{"normal":11,"urf":22}},"support":{"samples":{"normal":86,"urf":5},"wins":{"normal":41,"urf":0}}}},"Lulu":{"id":117,"key":"Lulu","name":"Lulu","title":"the Fae Sorceress","stats":{"total":{"samples":{"normal":6290,"urf":4217},"wins":{"normal":3032,"urf":2150}},"ad":{"samples":{"normal":157,"urf":214},"wins":{"normal":69,"urf":94}},"ap":{"samples":{"normal":2766,"urf":3887},"wins":{"normal":1398,"urf":2000}},"fighter":{"samples":{"normal":5,"urf":9},"wins":{"normal":2,"urf":5}},"tank":{"samples":{"normal":71,"urf":71},"wins":{"normal":31,"urf":33}},"support":{"samples":{"normal":3291,"urf":36},"wins":{"normal":1532,"urf":18}}}},"Karthus":{"id":30,"key":"Karthus","name":"Karthus","title":"the Deathsinger","stats":{"total":{"samples":{"normal":1649,"urf":8756},"wins":{"normal":828,"urf":4443}},"ad":{"samples":{"normal":1,"urf":29},"wins":{"normal":0,"urf":9}},"ap":{"samples":{"normal":1638,"urf":8705},"wins":{"normal":824,"urf":4424}},"fighter":{"samples":{"normal":0,"urf":0},"wins":{"normal":0,"urf":0}},"tank":{"samples":{"normal":3,"urf":19},"wins":{"normal":2,"urf":9}},"support":{"samples":{"normal":7,"urf":3},"wins":{"normal":2,"urf":1}}}},"Alistar":{"id":12,"key":"Alistar","name":"Alistar","title":"the Minotaur","stats":{"total":{"samples":{"normal":3426,"urf":6627},"wins":{"normal":1653,"urf":3307}},"ad":{"samples":{"normal":5,"urf":78},"wins":{"normal":3,"urf":46}},"ap":{"samples":{"normal":134,"urf":4050},"wins":{"normal":54,"urf":2090}},"fighter":{"samples":{"normal":10,"urf":46},"wins":{"normal":5,"urf":23}},"tank":{"samples":{"normal":465,"urf":2245},"wins":{"normal":202,"urf":1050}},"support":{"samples":{"normal":2812,"urf":208},"wins":{"normal":1389,"urf":98}}}},"Darius":{"id":122,"key":"Darius","name":"Darius","title":"the Hand of Noxus","stats":{"total":{"samples":{"normal":4597,"urf":3423},"wins":{"normal":2289,"urf":1776}},"ad":{"samples":{"normal":46,"urf":361},"wins":{"normal":22,"urf":192}},"ap":{"samples":{"normal":4,"urf":6},"wins":{"normal":1,"urf":4}},"fighter":{"samples":{"normal":2986,"urf":2534},"wins":{"normal":1559,"urf":1335}},"tank":{"samples":{"normal":1508,"urf":515},"wins":{"normal":687,"urf":239}},"support":{"samples":{"normal":53,"urf":7},"wins":{"normal":20,"urf":6}}}},"Vayne":{"id":67,"key":"Vayne","name":"Vayne","title":"the Night Hunter","stats":{"total":{"samples":{"normal":14526,"urf":2455},"wins":{"normal":7147,"urf":1244}},"ad":{"samples":{"normal":14385,"urf":2408},"wins":{"normal":7091,"urf":1226}},"ap":{"samples":{"normal":7,"urf":2},"wins":{"normal":1,"urf":0}},"fighter":{"samples":{"normal":32,"urf":16},"wins":{"normal":11,"urf":9}},"tank":{"samples":{"normal":85,"urf":28},"wins":{"normal":43,"urf":9}},"support":{"samples":{"normal":17,"urf":1},"wins":{"normal":1,"urf":0}}}},"Varus":{"id":110,"key":"Varus","name":"Varus","title":"the Arrow of Retribution","stats":{"total":{"samples":{"normal":2594,"urf":2737},"wins":{"normal":1311,"urf":1212}},"ad":{"samples":{"normal":2499,"urf":2569},"wins":{"normal":1270,"urf":1146}},"ap":{"samples":{"normal":43,"urf":104},"wins":{"normal":19,"urf":39}},"fighter":{"samples":{"normal":39,"urf":56},"wins":{"normal":19,"urf":25}},"tank":{"samples":{"normal":9,"urf":7},"wins":{"normal":2,"urf":2}},"support":{"samples":{"normal":4,"urf":1},"wins":{"normal":1,"urf":0}}}},"Udyr":{"id":77,"key":"Udyr","name":"Udyr","title":"the Spirit Walker","stats":{"total":{"samples":{"normal":6985,"urf":2482},"wins":{"normal":3590,"urf":1228}},"ad":{"samples":{"normal":71,"urf":342},"wins":{"normal":41,"urf":185}},"ap":{"samples":{"normal":26,"urf":138},"wins":{"normal":12,"urf":62}},"fighter":{"samples":{"normal":345,"urf":357},"wins":{"normal":166,"urf":198}},"tank":{"samples":{"normal":6489,"urf":1628},"wins":{"normal":3355,"urf":776}},"support":{"samples":{"normal":54,"urf":17},"wins":{"normal":16,"urf":7}}}},"Jayce":{"id":126,"key":"Jayce","name":"Jayce","title":"the Defender of Tomorrow","stats":{"total":{"samples":{"normal":1936,"urf":6479},"wins":{"normal":902,"urf":3094}},"ad":{"samples":{"normal":530,"urf":5310},"wins":{"normal":276,"urf":2575}},"ap":{"samples":{"normal":3,"urf":23},"wins":{"normal":0,"urf":7}},"fighter":{"samples":{"normal":1325,"urf":1059},"wins":{"normal":596,"urf":477}},"tank":{"samples":{"normal":69,"urf":87},"wins":{"normal":29,"urf":35}},"support":{"samples":{"normal":9,"urf":0},"wins":{"normal":1,"urf":0}}}},"Leona":{"id":89,"key":"Leona","name":"Leona","title":"the Radiant Dawn","stats":{"total":{"samples":{"normal":11496,"urf":5284},"wins":{"normal":6104,"urf":2592}},"ad":{"samples":{"normal":20,"urf":221},"wins":{"normal":7,"urf":114}},"ap":{"samples":{"normal":52,"urf":1554},"wins":{"normal":22,"urf":780}},"fighter":{"samples":{"normal":85,"urf":370},"wins":{"normal":38,"urf":185}},"tank":{"samples":{"normal":1169,"urf":2507},"wins":{"normal":589,"urf":1203}},"support":{"samples":{"normal":10170,"urf":632},"wins":{"normal":5448,"urf":310}}}},"Syndra":{"id":134,"key":"Syndra","name":"Syndra","title":"the Dark Sovereign","stats":{"total":{"samples":{"normal":1678,"urf":3908},"wins":{"normal":774,"urf":1889}},"ad":{"samples":{"normal":1,"urf":7},"wins":{"normal":0,"urf":5}},"ap":{"samples":{"normal":1656,"urf":3889},"wins":{"normal":770,"urf":1878}},"fighter":{"samples":{"normal":1,"urf":2},"wins":{"normal":0,"urf":1}},"tank":{"samples":{"normal":0,"urf":10},"wins":{"normal":0,"urf":5}},"support":{"samples":{"normal":20,"urf":0},"wins":{"normal":4,"urf":0}}}},"Pantheon":{"id":80,"key":"Pantheon","name":"Pantheon","title":"the Artisan of War","stats":{"total":{"samples":{"normal":4362,"urf":4215},"wins":{"normal":2129,"urf":1965}},"ad":{"samples":{"normal":113,"urf":772},"wins":{"normal":62,"urf":375}},"ap":{"samples":{"normal":12,"urf":707},"wins":{"normal":4,"urf":314}},"fighter":{"samples":{"normal":3888,"urf":2563},"wins":{"normal":1927,"urf":1200}},"tank":{"samples":{"normal":298,"urf":169},"wins":{"normal":117,"urf":74}},"support":{"samples":{"normal":51,"urf":4},"wins":{"normal":19,"urf":2}}}},"Khazix":{"id":121,"key":"Khazix","name":"Kha'Zix","title":"the Voidreaver","stats":{"total":{"samples":{"normal":2701,"urf":2615},"wins":{"normal":1233,"urf":1316}},"ad":{"samples":{"normal":20,"urf":417},"wins":{"normal":11,"urf":234}},"ap":{"samples":{"normal":5,"urf":9},"wins":{"normal":0,"urf":4}},"fighter":{"samples":{"normal":2618,"urf":2139},"wins":{"normal":1200,"urf":1056}},"tank":{"samples":{"normal":53,"urf":46},"wins":{"normal":21,"urf":20}},"support":{"samples":{"normal":5,"urf":4},"wins":{"normal":1,"urf":2}}}},"Riven":{"id":92,"key":"Riven","name":"Riven","title":"the Exile","stats":{"total":{"samples":{"normal":9169,"urf":6964},"wins":{"normal":4654,"urf":3461}},"ad":{"samples":{"normal":185,"urf":939},"wins":{"normal":104,"urf":493}},"ap":{"samples":{"normal":10,"urf":9},"wins":{"normal":3,"urf":4}},"fighter":{"samples":{"normal":8886,"urf":5908},"wins":{"normal":4521,"urf":2924}},"tank":{"samples":{"normal":63,"urf":103},"wins":{"normal":19,"urf":40}},"support":{"samples":{"normal":25,"urf":5},"wins":{"normal":7,"urf":0}}}},"Corki":{"id":42,"key":"Corki","name":"Corki","title":"the Daring Bombardier","stats":{"total":{"samples":{"normal":4700,"urf":1663},"wins":{"normal":2249,"urf":763}},"ad":{"samples":{"normal":2899,"urf":836},"wins":{"normal":1498,"urf":424}},"ap":{"samples":{"normal":264,"urf":714},"wins":{"normal":115,"urf":299}},"fighter":{"samples":{"normal":13,"urf":11},"wins":{"normal":4,"urf":6}},"tank":{"samples":{"normal":1522,"urf":100},"wins":{"normal":632,"urf":33}},"support":{"samples":{"normal":2,"urf":2},"wins":{"normal":0,"urf":1}}}},"Azir":{"id":268,"key":"Azir","name":"Azir","title":"the Emperor of the Sands","stats":{"total":{"samples":{"normal":1969,"urf":4679},"wins":{"normal":888,"urf":2329}},"ad":{"samples":{"normal":2,"urf":26},"wins":{"normal":0,"urf":10}},"ap":{"samples":{"normal":1941,"urf":4621},"wins":{"normal":879,"urf":2298}},"fighter":{"samples":{"normal":1,"urf":0},"wins":{"normal":0,"urf":0}},"tank":{"samples":{"normal":4,"urf":30},"wins":{"normal":2,"urf":21}},"support":{"samples":{"normal":21,"urf":2},"wins":{"normal":7,"urf":0}}}},"Caitlyn":{"id":51,"key":"Caitlyn","name":"Caitlyn","title":"the Sheriff of Piltover","stats":{"total":{"samples":{"normal":10761,"urf":2283},"wins":{"normal":5200,"urf":1041}},"ad":{"samples":{"normal":10709,"urf":2146},"wins":{"normal":5186,"urf":978}},"ap":{"samples":{"normal":21,"urf":117},"wins":{"normal":6,"urf":53}},"fighter":{"samples":{"normal":13,"urf":14},"wins":{"normal":4,"urf":7}},"tank":{"samples":{"normal":4,"urf":5},"wins":{"normal":2,"urf":3}},"support":{"samples":{"normal":14,"urf":1},"wins":{"normal":2,"urf":0}}}},"Nidalee":{"id":76,"key":"Nidalee","name":"Nidalee","title":"the Bestial Huntress","stats":{"total":{"samples":{"normal":7804,"urf":16648},"wins":{"normal":3642,"urf":8027}},"ad":{"samples":{"normal":48,"urf":101},"wins":{"normal":25,"urf":52}},"ap":{"samples":{"normal":7218,"urf":16434},"wins":{"normal":3434,"urf":7930}},"fighter":{"samples":{"normal":16,"urf":13},"wins":{"normal":6,"urf":6}},"tank":{"samples":{"normal":369,"urf":93},"wins":{"normal":132,"urf":36}},"support":{"samples":{"normal":153,"urf":7},"wins":{"normal":45,"urf":3}}}},"Galio":{"id":3,"key":"Galio","name":"Galio","title":"the Sentinel's Sorrow","stats":{"total":{"samples":{"normal":734,"urf":2959},"wins":{"normal":388,"urf":1616}},"ad":{"samples":{"normal":1,"urf":3},"wins":{"normal":0,"urf":0}},"ap":{"samples":{"normal":454,"urf":2243},"wins":{"normal":255,"urf":1241}},"fighter":{"samples":{"normal":2,"urf":2},"wins":{"normal":1,"urf":1}},"tank":{"samples":{"normal":179,"urf":699},"wins":{"normal":89,"urf":368}},"support":{"samples":{"normal":98,"urf":12},"wins":{"normal":43,"urf":6}}}},"Kennen":{"id":85,"key":"Kennen","name":"Kennen","title":"the Heart of the Tempest","stats":{"total":{"samples":{"normal":3149,"urf":2471},"wins":{"normal":1608,"urf":1325}},"ad":{"samples":{"normal":92,"urf":44},"wins":{"normal":40,"urf":24}},"ap":{"samples":{"normal":2885,"urf":2413},"wins":{"normal":1504,"urf":1295}},"fighter":{"samples":{"normal":2,"urf":2},"wins":{"normal":0,"urf":2}},"tank":{"samples":{"normal":10,"urf":11},"wins":{"normal":4,"urf":4}},"support":{"samples":{"normal":160,"urf":1},"wins":{"normal":60,"urf":0}}}},"Veigar":{"id":45,"key":"Veigar","name":"Veigar","title":"the Tiny Master of Evil","stats":{"total":{"samples":{"normal":1732,"urf":6355},"wins":{"normal":850,"urf":3257}},"ad":{"samples":{"normal":1,"urf":11},"wins":{"normal":0,"urf":4}},"ap":{"samples":{"normal":1660,"urf":6324},"wins":{"normal":824,"urf":3243}},"fighter":{"samples":{"normal":0,"urf":0},"wins":{"normal":0,"urf":0}},"tank":{"samples":{"normal":4,"urf":19},"wins":{"normal":2,"urf":10}},"support":{"samples":{"normal":67,"urf":1},"wins":{"normal":24,"urf":0}}}},"Bard":{"id":432,"key":"Bard","name":"Bard","title":"the Wandering Caretaker","stats":{"total":{"samples":{"normal":5141,"urf":4443},"wins":{"normal":2176,"urf":1934}},"ad":{"samples":{"normal":83,"urf":381},"wins":{"normal":33,"urf":180}},"ap":{"samples":{"normal":306,"urf":2755},"wins":{"normal":135,"urf":1199}},"fighter":{"samples":{"normal":17,"urf":12},"wins":{"normal":3,"urf":5}},"tank":{"samples":{"normal":282,"urf":702},"wins":{"normal":139,"urf":306}},"support":{"samples":{"normal":4453,"urf":593},"wins":{"normal":1866,"urf":244}}}},"Gnar":{"id":150,"key":"Gnar","name":"Gnar","title":"the Missing Link","stats":{"total":{"samples":{"normal":2946,"urf":1199},"wins":{"normal":1409,"urf":594}},"ad":{"samples":{"normal":106,"urf":241},"wins":{"normal":41,"urf":124}},"ap":{"samples":{"normal":6,"urf":26},"wins":{"normal":3,"urf":10}},"fighter":{"samples":{"normal":181,"urf":108},"wins":{"normal":84,"urf":56}},"tank":{"samples":{"normal":2617,"urf":823},"wins":{"normal":1267,"urf":403}},"support":{"samples":{"normal":36,"urf":1},"wins":{"normal":14,"urf":1}}}},"Graves":{"id":104,"key":"Graves","name":"Graves","title":"the Outlaw","stats":{"total":{"samples":{"normal":14518,"urf":2106},"wins":{"normal":7297,"urf":1026}},"ad":{"samples":{"normal":14398,"urf":2056},"wins":{"normal":7268,"urf":1005}},"ap":{"samples":{"normal":13,"urf":16},"wins":{"normal":3,"urf":7}},"fighter":{"samples":{"normal":89,"urf":22},"wins":{"normal":24,"urf":8}},"tank":{"samples":{"normal":5,"urf":11},"wins":{"normal":2,"urf":6}},"support":{"samples":{"normal":13,"urf":1},"wins":{"normal":0,"urf":0}}}},"Malzahar":{"id":90,"key":"Malzahar","name":"Malzahar","title":"the Prophet of the Void","stats":{"total":{"samples":{"normal":3151,"urf":6167},"wins":{"normal":1730,"urf":3056}},"ad":{"samples":{"normal":26,"urf":2411},"wins":{"normal":11,"urf":1150}},"ap":{"samples":{"normal":3014,"urf":3195},"wins":{"normal":1669,"urf":1635}},"fighter":{"samples":{"normal":81,"urf":442},"wins":{"normal":40,"urf":212}},"tank":{"samples":{"normal":16,"urf":113},"wins":{"normal":5,"urf":57}},"support":{"samples":{"normal":14,"urf":6},"wins":{"normal":5,"urf":2}}}},"Vi":{"id":254,"key":"Vi","name":"Vi","title":"the Piltover Enforcer","stats":{"total":{"samples":{"normal":7646,"urf":3948},"wins":{"normal":3842,"urf":2081}},"ad":{"samples":{"normal":51,"urf":625},"wins":{"normal":35,"urf":343}},"ap":{"samples":{"normal":6,"urf":21},"wins":{"normal":1,"urf":10}},"fighter":{"samples":{"normal":2954,"urf":1166},"wins":{"normal":1300,"urf":616}},"tank":{"samples":{"normal":4601,"urf":2126},"wins":{"normal":2494,"urf":1109}},"support":{"samples":{"normal":34,"urf":10},"wins":{"normal":12,"urf":3}}}},"Kayle":{"id":10,"key":"Kayle","name":"Kayle","title":"The Judicator","stats":{"total":{"samples":{"normal":1530,"urf":2869},"wins":{"normal":792,"urf":1466}},"ad":{"samples":{"normal":174,"urf":272},"wins":{"normal":76,"urf":136}},"ap":{"samples":{"normal":1161,"urf":2459},"wins":{"normal":616,"urf":1253}},"fighter":{"samples":{"normal":9,"urf":25},"wins":{"normal":3,"urf":16}},"tank":{"samples":{"normal":72,"urf":110},"wins":{"normal":42,"urf":59}},"support":{"samples":{"normal":114,"urf":3},"wins":{"normal":55,"urf":2}}}},"Irelia":{"id":39,"key":"Irelia","name":"Irelia","title":"the Will of the Blades","stats":{"total":{"samples":{"normal":4968,"urf":1707},"wins":{"normal":2609,"urf":890}},"ad":{"samples":{"normal":81,"urf":259},"wins":{"normal":39,"urf":150}},"ap":{"samples":{"normal":8,"urf":37},"wins":{"normal":4,"urf":16}},"fighter":{"samples":{"normal":71,"urf":209},"wins":{"normal":34,"urf":124}},"tank":{"samples":{"normal":4765,"urf":1201},"wins":{"normal":2518,"urf":600}},"support":{"samples":{"normal":43,"urf":1},"wins":{"normal":14,"urf":0}}}},"LeeSin":{"id":64,"key":"LeeSin","name":"Lee Sin","title":"the Blind Monk","stats":{"total":{"samples":{"normal":13834,"urf":3855},"wins":{"normal":6394,"urf":1786}},"ad":{"samples":{"normal":55,"urf":383},"wins":{"normal":24,"urf":214}},"ap":{"samples":{"normal":21,"urf":36},"wins":{"normal":9,"urf":11}},"fighter":{"samples":{"normal":11716,"urf":3238},"wins":{"normal":5492,"urf":1467}},"tank":{"samples":{"normal":1601,"urf":191},"wins":{"normal":722,"urf":90}},"support":{"samples":{"normal":441,"urf":7},"wins":{"normal":147,"urf":4}}}},"Elise":{"id":60,"key":"Elise","name":"Elise","title":"The Spider Queen","stats":{"total":{"samples":{"normal":1258,"urf":719},"wins":{"normal":559,"urf":329}},"ad":{"samples":{"normal":3,"urf":17},"wins":{"normal":0,"urf":5}},"ap":{"samples":{"normal":479,"urf":634},"wins":{"normal":207,"urf":294}},"fighter":{"samples":{"normal":4,"urf":8},"wins":{"normal":2,"urf":4}},"tank":{"samples":{"normal":715,"urf":56},"wins":{"normal":325,"urf":23}},"support":{"samples":{"normal":57,"urf":4},"wins":{"normal":25,"urf":3}}}},"Volibear":{"id":106,"key":"Volibear","name":"Volibear","title":"the Thunder's Roar","stats":{"total":{"samples":{"normal":5075,"urf":1539},"wins":{"normal":2713,"urf":749}},"ad":{"samples":{"normal":19,"urf":70},"wins":{"normal":8,"urf":36}},"ap":{"samples":{"normal":10,"urf":45},"wins":{"normal":4,"urf":26}},"fighter":{"samples":{"normal":47,"urf":102},"wins":{"normal":22,"urf":52}},"tank":{"samples":{"normal":4730,"urf":1317},"wins":{"normal":2546,"urf":632}},"support":{"samples":{"normal":269,"urf":5},"wins":{"normal":133,"urf":3}}}},"Nunu":{"id":20,"key":"Nunu","name":"Nunu","title":"the Yeti Rider","stats":{"total":{"samples":{"normal":3571,"urf":2389},"wins":{"normal":1920,"urf":1140}},"ad":{"samples":{"normal":4,"urf":21},"wins":{"normal":1,"urf":11}},"ap":{"samples":{"normal":600,"urf":1997},"wins":{"normal":283,"urf":964}},"fighter":{"samples":{"normal":2,"urf":9},"wins":{"normal":0,"urf":2}},"tank":{"samples":{"normal":2563,"urf":351},"wins":{"normal":1451,"urf":159}},"support":{"samples":{"normal":402,"urf":11},"wins":{"normal":185,"urf":4}}}},"TwistedFate":{"id":4,"key":"TwistedFate","name":"Twisted Fate","title":"the Card Master","stats":{"total":{"samples":{"normal":3748,"urf":5220},"wins":{"normal":1840,"urf":2625}},"ad":{"samples":{"normal":299,"urf":299},"wins":{"normal":134,"urf":138}},"ap":{"samples":{"normal":3332,"urf":4866},"wins":{"normal":1668,"urf":2470}},"fighter":{"samples":{"normal":3,"urf":9},"wins":{"normal":1,"urf":3}},"tank":{"samples":{"normal":72,"urf":41},"wins":{"normal":24,"urf":14}},"support":{"samples":{"normal":42,"urf":5},"wins":{"normal":13,"urf":0}}}},"Jax":{"id":24,"key":"Jax","name":"Jax","title":"Grandmaster at Arms","stats":{"total":{"samples":{"normal":3731,"urf":6594},"wins":{"normal":1758,"urf":3664}},"ad":{"samples":{"normal":206,"urf":810},"wins":{"normal":84,"urf":499}},"ap":{"samples":{"normal":34,"urf":1251},"wins":{"normal":16,"urf":711}},"fighter":{"samples":{"normal":325,"urf":1949},"wins":{"normal":157,"urf":1110}},"tank":{"samples":{"normal":3152,"urf":2576},"wins":{"normal":1499,"urf":1342}},"support":{"samples":{"normal":14,"urf":8},"wins":{"normal":2,"urf":2}}}},"Shyvana":{"id":102,"key":"Shyvana","name":"Shyvana","title":"the Half-Dragon","stats":{"total":{"samples":{"normal":5087,"urf":828},"wins":{"normal":2468,"urf":423}},"ad":{"samples":{"normal":50,"urf":72},"wins":{"normal":22,"urf":40}},"ap":{"samples":{"normal":6,"urf":33},"wins":{"normal":1,"urf":19}},"fighter":{"samples":{"normal":427,"urf":375},"wins":{"normal":237,"urf":191}},"tank":{"samples":{"normal":4596,"urf":347},"wins":{"normal":2206,"urf":172}},"support":{"samples":{"normal":8,"urf":1},"wins":{"normal":2,"urf":1}}}},"Kalista":{"id":429,"key":"Kalista","name":"Kalista","title":"the Spear of Vengeance","stats":{"total":{"samples":{"normal":6407,"urf":884},"wins":{"normal":3177,"urf":378}},"ad":{"samples":{"normal":6365,"urf":864},"wins":{"normal":3162,"urf":371}},"ap":{"samples":{"normal":4,"urf":4},"wins":{"normal":1,"urf":2}},"fighter":{"samples":{"normal":18,"urf":5},"wins":{"normal":8,"urf":1}},"tank":{"samples":{"normal":5,"urf":9},"wins":{"normal":1,"urf":4}},"support":{"samples":{"normal":15,"urf":2},"wins":{"normal":5,"urf":0}}}},"DrMundo":{"id":36,"key":"DrMundo","name":"Dr. Mundo","title":"the Madman of Zaun","stats":{"total":{"samples":{"normal":2038,"urf":3603},"wins":{"normal":950,"urf":1764}},"ad":{"samples":{"normal":4,"urf":28},"wins":{"normal":2,"urf":16}},"ap":{"samples":{"normal":3,"urf":78},"wins":{"normal":2,"urf":33}},"fighter":{"samples":{"normal":11,"urf":72},"wins":{"normal":4,"urf":44}},"tank":{"samples":{"normal":1946,"urf":3409},"wins":{"normal":910,"urf":1664}},"support":{"samples":{"normal":74,"urf":16},"wins":{"normal":32,"urf":7}}}},"Brand":{"id":63,"key":"Brand","name":"Brand","title":"the Burning Vengeance","stats":{"total":{"samples":{"normal":2616,"urf":3740},"wins":{"normal":1356,"urf":1709}},"ad":{"samples":{"normal":3,"urf":20},"wins":{"normal":1,"urf":6}},"ap":{"samples":{"normal":2509,"urf":3704},"wins":{"normal":1314,"urf":1696}},"fighter":{"samples":{"normal":0,"urf":1},"wins":{"normal":0,"urf":0}},"tank":{"samples":{"normal":3,"urf":14},"wins":{"normal":3,"urf":7}},"support":{"samples":{"normal":101,"urf":1},"wins":{"normal":38,"urf":0}}}},"Diana":{"id":131,"key":"Diana","name":"Diana","title":"Scorn of the Moon","stats":{"total":{"samples":{"normal":4808,"urf":3998},"wins":{"normal":2458,"urf":2127}},"ad":{"samples":{"normal":2,"urf":23},"wins":{"normal":1,"urf":11}},"ap":{"samples":{"normal":4713,"urf":3941},"wins":{"normal":2424,"urf":2102}},"fighter":{"samples":{"normal":3,"urf":2},"wins":{"normal":1,"urf":2}},"tank":{"samples":{"normal":79,"urf":29},"wins":{"normal":28,"urf":12}},"support":{"samples":{"normal":11,"urf":3},"wins":{"normal":4,"urf":0}}}},"Sejuani":{"id":113,"key":"Sejuani","name":"Sejuani","title":"the Winter's Wrath","stats":{"total":{"samples":{"normal":7726,"urf":3442},"wins":{"normal":4329,"urf":1817}},"ad":{"samples":{"normal":4,"urf":13},"wins":{"normal":3,"urf":8}},"ap":{"samples":{"normal":243,"urf":1864},"wins":{"normal":121,"urf":999}},"fighter":{"samples":{"normal":4,"urf":20},"wins":{"normal":1,"urf":10}},"tank":{"samples":{"normal":7257,"urf":1522},"wins":{"normal":4118,"urf":789}},"support":{"samples":{"normal":218,"urf":23},"wins":{"normal":86,"urf":11}}}},"Vladimir":{"id":8,"key":"Vladimir","name":"Vladimir","title":"the Crimson Reaper","stats":{"total":{"samples":{"normal":7233,"urf":6187},"wins":{"normal":3624,"urf":3112}},"ad":{"samples":{"normal":4,"urf":9},"wins":{"normal":1,"urf":7}},"ap":{"samples":{"normal":6674,"urf":5690},"wins":{"normal":3394,"urf":2876}},"fighter":{"samples":{"normal":1,"urf":1},"wins":{"normal":1,"urf":0}},"tank":{"samples":{"normal":540,"urf":487},"wins":{"normal":223,"urf":229}},"support":{"samples":{"normal":14,"urf":0},"wins":{"normal":5,"urf":0}}}},"Zac":{"id":154,"key":"Zac","name":"Zac","title":"the Secret Weapon","stats":{"total":{"samples":{"normal":2671,"urf":1054},"wins":{"normal":1314,"urf":558}},"ad":{"samples":{"normal":1,"urf":0},"wins":{"normal":0,"urf":0}},"ap":{"samples":{"normal":73,"urf":429},"wins":{"normal":42,"urf":226}},"fighter":{"samples":{"normal":1,"urf":2},"wins":{"normal":0,"urf":2}},"tank":{"samples":{"normal":2550,"urf":618},"wins":{"normal":1250,"urf":328}},"support":{"samples":{"normal":46,"urf":5},"wins":{"normal":22,"urf":2}}}},"RekSai":{"id":421,"key":"RekSai","name":"Rek'Sai","title":"the Void Burrower","stats":{"total":{"samples":{"normal":4261,"urf":1734},"wins":{"normal":2089,"urf":773}},"ad":{"samples":{"normal":28,"urf":77},"wins":{"normal":18,"urf":34}},"ap":{"samples":{"normal":19,"urf":953},"wins":{"normal":2,"urf":429}},"fighter":{"samples":{"normal":2574,"urf":517},"wins":{"normal":1277,"urf":221}},"tank":{"samples":{"normal":1627,"urf":185},"wins":{"normal":787,"urf":88}},"support":{"samples":{"normal":13,"urf":2},"wins":{"normal":5,"urf":1}}}},"Quinn":{"id":133,"key":"Quinn","name":"Quinn","title":"Demacia's Wings","stats":{"total":{"samples":{"normal":3423,"urf":1907},"wins":{"normal":1739,"urf":949}},"ad":{"samples":{"normal":3086,"urf":1811},"wins":{"normal":1584,"urf":901}},"ap":{"samples":{"normal":5,"urf":5},"wins":{"normal":2,"urf":3}},"fighter":{"samples":{"normal":240,"urf":51},"wins":{"normal":106,"urf":23}},"tank":{"samples":{"normal":85,"urf":38},"wins":{"normal":43,"urf":22}},"support":{"samples":{"normal":7,"urf":2},"wins":{"normal":4,"urf":0}}}},"Akali":{"id":84,"key":"Akali","name":"Akali","title":"the Fist of Shadow","stats":{"total":{"samples":{"normal":2249,"urf":4120},"wins":{"normal":1036,"urf":2005}},"ad":{"samples":{"normal":5,"urf":54},"wins":{"normal":0,"urf":21}},"ap":{"samples":{"normal":2134,"urf":3965},"wins":{"normal":996,"urf":1935}},"fighter":{"samples":{"normal":10,"urf":42},"wins":{"normal":4,"urf":19}},"tank":{"samples":{"normal":84,"urf":51},"wins":{"normal":33,"urf":28}},"support":{"samples":{"normal":16,"urf":8},"wins":{"normal":3,"urf":2}}}},"Tristana":{"id":18,"key":"Tristana","name":"Tristana","title":"the Yordle Gunner","stats":{"total":{"samples":{"normal":4909,"urf":2041},"wins":{"normal":2286,"urf":980}},"ad":{"samples":{"normal":4845,"urf":1681},"wins":{"normal":2265,"urf":816}},"ap":{"samples":{"normal":34,"urf":331},"wins":{"normal":12,"urf":152}},"fighter":{"samples":{"normal":13,"urf":10},"wins":{"normal":5,"urf":3}},"tank":{"samples":{"normal":10,"urf":17},"wins":{"normal":2,"urf":8}},"support":{"samples":{"normal":7,"urf":2},"wins":{"normal":2,"urf":1}}}},"Hecarim":{"id":120,"key":"Hecarim","name":"Hecarim","title":"the Shadow of War","stats":{"total":{"samples":{"normal":6401,"urf":12517},"wins":{"normal":3225,"urf":6531}},"ad":{"samples":{"normal":47,"urf":1947},"wins":{"normal":25,"urf":1079}},"ap":{"samples":{"normal":13,"urf":155},"wins":{"normal":4,"urf":78}},"fighter":{"samples":{"normal":351,"urf":1961},"wins":{"normal":157,"urf":1020}},"tank":{"samples":{"normal":5941,"urf":8302},"wins":{"normal":3029,"urf":4280}},"support":{"samples":{"normal":49,"urf":152},"wins":{"normal":10,"urf":74}}}},"Sivir":{"id":15,"key":"Sivir","name":"Sivir","title":"the Battle Mistress","stats":{"total":{"samples":{"normal":7092,"urf":4302},"wins":{"normal":3766,"urf":2151}},"ad":{"samples":{"normal":7044,"urf":4227},"wins":{"normal":3754,"urf":2114}},"ap":{"samples":{"normal":3,"urf":17},"wins":{"normal":1,"urf":9}},"fighter":{"samples":{"normal":24,"urf":33},"wins":{"normal":5,"urf":16}},"tank":{"samples":{"normal":12,"urf":22},"wins":{"normal":5,"urf":12}},"support":{"samples":{"normal":9,"urf":3},"wins":{"normal":1,"urf":0}}}},"Lucian":{"id":236,"key":"Lucian","name":"Lucian","title":"the Purifier","stats":{"total":{"samples":{"normal":11089,"urf":7712},"wins":{"normal":5388,"urf":3737}},"ad":{"samples":{"normal":10825,"urf":7077},"wins":{"normal":5298,"urf":3473}},"ap":{"samples":{"normal":24,"urf":507},"wins":{"normal":9,"urf":223}},"fighter":{"samples":{"normal":148,"urf":56},"wins":{"normal":45,"urf":18}},"tank":{"samples":{"normal":83,"urf":68},"wins":{"normal":36,"urf":22}},"support":{"samples":{"normal":9,"urf":4},"wins":{"normal":0,"urf":1}}}},"Rengar":{"id":107,"key":"Rengar","name":"Rengar","title":"the Pridestalker","stats":{"total":{"samples":{"normal":4782,"urf":2931},"wins":{"normal":2270,"urf":1510}},"ad":{"samples":{"normal":215,"urf":785},"wins":{"normal":118,"urf":436}},"ap":{"samples":{"normal":39,"urf":340},"wins":{"normal":16,"urf":170}},"fighter":{"samples":{"normal":4205,"urf":1719},"wins":{"normal":1998,"urf":861}},"tank":{"samples":{"normal":287,"urf":84},"wins":{"normal":122,"urf":42}},"support":{"samples":{"normal":36,"urf":3},"wins":{"normal":16,"urf":1}}}},"Warwick":{"id":19,"key":"Warwick","name":"Warwick","title":"the Blood Hunter","stats":{"total":{"samples":{"normal":3436,"urf":2645},"wins":{"normal":1728,"urf":1386}},"ad":{"samples":{"normal":208,"urf":370},"wins":{"normal":105,"urf":197}},"ap":{"samples":{"normal":69,"urf":847},"wins":{"normal":25,"urf":477}},"fighter":{"samples":{"normal":195,"urf":371},"wins":{"normal":105,"urf":200}},"tank":{"samples":{"normal":2882,"urf":1049},"wins":{"normal":1465,"urf":508}},"support":{"samples":{"normal":82,"urf":8},"wins":{"normal":28,"urf":4}}}},"Skarner":{"id":72,"key":"Skarner","name":"Skarner","title":"the Crystal Vanguard","stats":{"total":{"samples":{"normal":1590,"urf":1597},"wins":{"normal":827,"urf":837}},"ad":{"samples":{"normal":3,"urf":120},"wins":{"normal":1,"urf":70}},"ap":{"samples":{"normal":6,"urf":331},"wins":{"normal":3,"urf":176}},"fighter":{"samples":{"normal":40,"urf":200},"wins":{"normal":17,"urf":99}},"tank":{"samples":{"normal":1504,"urf":916},"wins":{"normal":791,"urf":478}},"support":{"samples":{"normal":37,"urf":30},"wins":{"normal":15,"urf":14}}}},"Malphite":{"id":54,"key":"Malphite","name":"Malphite","title":"Shard of the Monolith","stats":{"total":{"samples":{"normal":5492,"urf":9246},"wins":{"normal":2858,"urf":4564}},"ad":{"samples":{"normal":31,"urf":69},"wins":{"normal":18,"urf":26}},"ap":{"samples":{"normal":927,"urf":7505},"wins":{"normal":486,"urf":3743}},"fighter":{"samples":{"normal":55,"urf":39},"wins":{"normal":34,"urf":17}},"tank":{"samples":{"normal":3840,"urf":1609},"wins":{"normal":2004,"urf":770}},"support":{"samples":{"normal":639,"urf":24},"wins":{"normal":316,"urf":8}}}},"Yasuo":{"id":157,"key":"Yasuo","name":"Yasuo","title":"the Unforgiven","stats":{"total":{"samples":{"normal":9640,"urf":2706},"wins":{"normal":4636,"urf":1316}},"ad":{"samples":{"normal":9429,"urf":2625},"wins":{"normal":4559,"urf":1277}},"ap":{"samples":{"normal":14,"urf":8},"wins":{"normal":6,"urf":6}},"fighter":{"samples":{"normal":102,"urf":46},"wins":{"normal":34,"urf":23}},"tank":{"samples":{"normal":76,"urf":27},"wins":{"normal":31,"urf":10}},"support":{"samples":{"normal":19,"urf":0},"wins":{"normal":6,"urf":0}}}},"Xerath":{"id":101,"key":"Xerath","name":"Xerath","title":"the Magus Ascendant","stats":{"total":{"samples":{"normal":3164,"urf":3030},"wins":{"normal":1523,"urf":1397}},"ad":{"samples":{"normal":4,"urf":17},"wins":{"normal":1,"urf":9}},"ap":{"samples":{"normal":3125,"urf":2999},"wins":{"normal":1511,"urf":1383}},"fighter":{"samples":{"normal":1,"urf":1},"wins":{"normal":0,"urf":1}},"tank":{"samples":{"normal":1,"urf":11},"wins":{"normal":0,"urf":4}},"support":{"samples":{"normal":33,"urf":2},"wins":{"normal":11,"urf":0}}}},"Teemo":{"id":17,"key":"Teemo","name":"Teemo","title":"the Swift Scout","stats":{"total":{"samples":{"normal":10268,"urf":16555},"wins":{"normal":5148,"urf":8511}},"ad":{"samples":{"normal":607,"urf":300},"wins":{"normal":260,"urf":140}},"ap":{"samples":{"normal":9115,"urf":16119},"wins":{"normal":4667,"urf":8313}},"fighter":{"samples":{"normal":20,"urf":15},"wins":{"normal":12,"urf":3}},"tank":{"samples":{"normal":363,"urf":109},"wins":{"normal":160,"urf":51}},"support":{"samples":{"normal":163,"urf":12},"wins":{"normal":49,"urf":4}}}},"Nasus":{"id":75,"key":"Nasus","name":"Nasus","title":"the Curator of the Sands","stats":{"total":{"samples":{"normal":7781,"urf":7979},"wins":{"normal":4081,"urf":4065}},"ad":{"samples":{"normal":56,"urf":1003},"wins":{"normal":31,"urf":557}},"ap":{"samples":{"normal":105,"urf":1532},"wins":{"normal":46,"urf":702}},"fighter":{"samples":{"normal":80,"urf":559},"wins":{"normal":37,"urf":315}},"tank":{"samples":{"normal":7235,"urf":4861},"wins":{"normal":3850,"urf":2479}},"support":{"samples":{"normal":305,"urf":24},"wins":{"normal":117,"urf":12}}}},"Renekton":{"id":58,"key":"Renekton","name":"Renekton","title":"the Butcher of the Sands","stats":{"total":{"samples":{"normal":2738,"urf":1084},"wins":{"normal":1373,"urf":511}},"ad":{"samples":{"normal":20,"urf":72},"wins":{"normal":12,"urf":39}},"ap":{"samples":{"normal":4,"urf":7},"wins":{"normal":1,"urf":1}},"fighter":{"samples":{"normal":1580,"urf":797},"wins":{"normal":870,"urf":382}},"tank":{"samples":{"normal":1119,"urf":207},"wins":{"normal":485,"urf":89}},"support":{"samples":{"normal":15,"urf":1},"wins":{"normal":5,"urf":0}}}},"Draven":{"id":119,"key":"Draven","name":"Draven","title":"the Glorious Executioner","stats":{"total":{"samples":{"normal":5720,"urf":1284},"wins":{"normal":2966,"urf":657}},"ad":{"samples":{"normal":5681,"urf":1274},"wins":{"normal":2956,"urf":654}},"ap":{"samples":{"normal":6,"urf":0},"wins":{"normal":2,"urf":0}},"fighter":{"samples":{"normal":25,"urf":8},"wins":{"normal":4,"urf":2}},"tank":{"samples":{"normal":6,"urf":2},"wins":{"normal":4,"urf":1}},"support":{"samples":{"normal":2,"urf":0},"wins":{"normal":0,"urf":0}}}},"Shaco":{"id":35,"key":"Shaco","name":"Shaco","title":"the Demon Jester","stats":{"total":{"samples":{"normal":5244,"urf":19011},"wins":{"normal":2546,"urf":9900}},"ad":{"samples":{"normal":999,"urf":2413},"wins":{"normal":534,"urf":1322}},"ap":{"samples":{"normal":1028,"urf":15899},"wins":{"normal":487,"urf":8281}},"fighter":{"samples":{"normal":3055,"urf":629},"wins":{"normal":1462,"urf":278}},"tank":{"samples":{"normal":89,"urf":62},"wins":{"normal":40,"urf":17}},"support":{"samples":{"normal":73,"urf":8},"wins":{"normal":23,"urf":2}}}},"Swain":{"id":50,"key":"Swain","name":"Swain","title":"the Master Tactician","stats":{"total":{"samples":{"normal":2969,"urf":4682},"wins":{"normal":1531,"urf":2296}},"ad":{"samples":{"normal":3,"urf":13},"wins":{"normal":1,"urf":5}},"ap":{"samples":{"normal":2899,"urf":4477},"wins":{"normal":1510,"urf":2213}},"fighter":{"samples":{"normal":1,"urf":0},"wins":{"normal":1,"urf":0}},"tank":{"samples":{"normal":45,"urf":188},"wins":{"normal":17,"urf":76}},"support":{"samples":{"normal":21,"urf":4},"wins":{"normal":2,"urf":2}}}},"Ziggs":{"id":115,"key":"Ziggs","name":"Ziggs","title":"the Hexplosives Expert","stats":{"total":{"samples":{"normal":2093,"urf":6780},"wins":{"normal":1039,"urf":3101}},"ad":{"samples":{"normal":3,"urf":28},"wins":{"normal":2,"urf":12}},"ap":{"samples":{"normal":2076,"urf":6740},"wins":{"normal":1032,"urf":3087}},"fighter":{"samples":{"normal":1,"urf":0},"wins":{"normal":0,"urf":0}},"tank":{"samples":{"normal":2,"urf":11},"wins":{"normal":1,"urf":2}},"support":{"samples":{"normal":11,"urf":1},"wins":{"normal":4,"urf":0}}}},"Janna":{"id":40,"key":"Janna","name":"Janna","title":"the Storm's Fury","stats":{"total":{"samples":{"normal":7013,"urf":1644},"wins":{"normal":3659,"urf":782}},"ad":{"samples":{"normal":26,"urf":38},"wins":{"normal":10,"urf":14}},"ap":{"samples":{"normal":437,"urf":1453},"wins":{"normal":255,"urf":703}},"fighter":{"samples":{"normal":0,"urf":1},"wins":{"normal":0,"urf":0}},"tank":{"samples":{"normal":38,"urf":37},"wins":{"normal":16,"urf":15}},"support":{"samples":{"normal":6512,"urf":115},"wins":{"normal":3378,"urf":50}}}},"Talon":{"id":91,"key":"Talon","name":"Talon","title":"the Blade's Shadow","stats":{"total":{"samples":{"normal":3051,"urf":4257},"wins":{"normal":1615,"urf":2253}},"ad":{"samples":{"normal":385,"urf":1805},"wins":{"normal":242,"urf":997}},"ap":{"samples":{"normal":3,"urf":5},"wins":{"normal":1,"urf":2}},"fighter":{"samples":{"normal":2641,"urf":2427},"wins":{"normal":1369,"urf":1242}},"tank":{"samples":{"normal":9,"urf":17},"wins":{"normal":2,"urf":9}},"support":{"samples":{"normal":13,"urf":3},"wins":{"normal":1,"urf":3}}}},"Orianna":{"id":61,"key":"Orianna","name":"Orianna","title":"the Lady of Clockwork","stats":{"total":{"samples":{"normal":4189,"urf":3161},"wins":{"normal":2034,"urf":1611}},"ad":{"samples":{"normal":5,"urf":3},"wins":{"normal":2,"urf":2}},"ap":{"samples":{"normal":4117,"urf":3150},"wins":{"normal":2009,"urf":1607}},"fighter":{"samples":{"normal":0,"urf":0},"wins":{"normal":0,"urf":0}},"tank":{"samples":{"normal":5,"urf":7},"wins":{"normal":1,"urf":2}},"support":{"samples":{"normal":62,"urf":1},"wins":{"normal":22,"urf":0}}}},"FiddleSticks":{"id":9,"key":"FiddleSticks","name":"Fiddlesticks","title":"the Harbinger of Doom","stats":{"total":{"samples":{"normal":3005,"urf":3811},"wins":{"normal":1511,"urf":1794}},"ad":{"samples":{"normal":12,"urf":33},"wins":{"normal":3,"urf":14}},"ap":{"samples":{"normal":2836,"urf":3748},"wins":{"normal":1462,"urf":1769}},"fighter":{"samples":{"normal":1,"urf":1},"wins":{"normal":0,"urf":0}},"tank":{"samples":{"normal":27,"urf":26},"wins":{"normal":9,"urf":11}},"support":{"samples":{"normal":129,"urf":3},"wins":{"normal":37,"urf":0}}}},"Fiora":{"id":114,"key":"Fiora","name":"Fiora","title":"the Grand Duelist","stats":{"total":{"samples":{"normal":3123,"urf":4137},"wins":{"normal":1708,"urf":2250}},"ad":{"samples":{"normal":543,"urf":2504},"wins":{"normal":311,"urf":1440}},"ap":{"samples":{"normal":1,"urf":5},"wins":{"normal":0,"urf":3}},"fighter":{"samples":{"normal":2560,"urf":1619},"wins":{"normal":1390,"urf":805}},"tank":{"samples":{"normal":16,"urf":6},"wins":{"normal":6,"urf":2}},"support":{"samples":{"normal":3,"urf":3},"wins":{"normal":1,"urf":0}}}},"Chogath":{"id":31,"key":"Chogath","name":"Cho'Gath","title":"the Terror of the Void","stats":{"total":{"samples":{"normal":8258,"urf":7612},"wins":{"normal":4187,"urf":3590}},"ad":{"samples":{"normal":8,"urf":36},"wins":{"normal":3,"urf":18}},"ap":{"samples":{"normal":5109,"urf":6222},"wins":{"normal":2736,"urf":2989}},"fighter":{"samples":{"normal":13,"urf":17},"wins":{"normal":7,"urf":8}},"tank":{"samples":{"normal":2903,"urf":1301},"wins":{"normal":1356,"urf":568}},"support":{"samples":{"normal":225,"urf":36},"wins":{"normal":85,"urf":7}}}},"Rammus":{"id":33,"key":"Rammus","name":"Rammus","title":"the Armordillo","stats":{"total":{"samples":{"normal":1786,"urf":1863},"wins":{"normal":929,"urf":968}},"ad":{"samples":{"normal":4,"urf":21},"wins":{"normal":1,"urf":14}},"ap":{"samples":{"normal":25,"urf":728},"wins":{"normal":10,"urf":367}},"fighter":{"samples":{"normal":10,"urf":24},"wins":{"normal":3,"urf":11}},"tank":{"samples":{"normal":1684,"urf":991},"wins":{"normal":883,"urf":519}},"support":{"samples":{"normal":63,"urf":99},"wins":{"normal":32,"urf":57}}}},"Leblanc":{"id":7,"key":"Leblanc","name":"LeBlanc","title":"the Deceiver","stats":{"total":{"samples":{"normal":7094,"urf":9147},"wins":{"normal":3319,"urf":4279}},"ad":{"samples":{"normal":63,"urf":84},"wins":{"normal":32,"urf":41}},"ap":{"samples":{"normal":6946,"urf":9022},"wins":{"normal":3264,"urf":4224}},"fighter":{"samples":{"normal":7,"urf":2},"wins":{"normal":1,"urf":1}},"tank":{"samples":{"normal":29,"urf":35},"wins":{"normal":11,"urf":12}},"support":{"samples":{"normal":49,"urf":4},"wins":{"normal":11,"urf":1}}}},"Zilean":{"id":26,"key":"Zilean","name":"Zilean","title":"the Chronokeeper","stats":{"total":{"samples":{"normal":828,"urf":2239},"wins":{"normal":384,"urf":1003}},"ad":{"samples":{"normal":2,"urf":23},"wins":{"normal":1,"urf":10}},"ap":{"samples":{"normal":476,"urf":2159},"wins":{"normal":231,"urf":965}},"fighter":{"samples":{"normal":1,"urf":0},"wins":{"normal":1,"urf":0}},"tank":{"samples":{"normal":7,"urf":33},"wins":{"normal":3,"urf":16}},"support":{"samples":{"normal":342,"urf":24},"wins":{"normal":148,"urf":12}}}},"Soraka":{"id":16,"key":"Soraka","name":"Soraka","title":"the Starchild","stats":{"total":{"samples":{"normal":2562,"urf":4323},"wins":{"normal":1281,"urf":2124}},"ad":{"samples":{"normal":19,"urf":86},"wins":{"normal":5,"urf":40}},"ap":{"samples":{"normal":387,"urf":3820},"wins":{"normal":213,"urf":1894}},"fighter":{"samples":{"normal":2,"urf":3},"wins":{"normal":1,"urf":1}},"tank":{"samples":{"normal":65,"urf":235},"wins":{"normal":23,"urf":117}},"support":{"samples":{"normal":2089,"urf":179},"wins":{"normal":1039,"urf":72}}}},"Nocturne":{"id":56,"key":"Nocturne","name":"Nocturne","title":"the Eternal Nightmare","stats":{"total":{"samples":{"normal":1835,"urf":1349},"wins":{"normal":932,"urf":724}},"ad":{"samples":{"normal":177,"urf":482},"wins":{"normal":93,"urf":257}},"ap":{"samples":{"normal":4,"urf":6},"wins":{"normal":2,"urf":2}},"fighter":{"samples":{"normal":988,"urf":747},"wins":{"normal":501,"urf":406}},"tank":{"samples":{"normal":658,"urf":114},"wins":{"normal":332,"urf":59}},"support":{"samples":{"normal":8,"urf":0},"wins":{"normal":4,"urf":0}}}},"Jinx":{"id":222,"key":"Jinx","name":"Jinx","title":"the Loose Cannon","stats":{"total":{"samples":{"normal":17440,"urf":10661},"wins":{"normal":9392,"urf":5025}},"ad":{"samples":{"normal":17392,"urf":10522},"wins":{"normal":9384,"urf":4970}},"ap":{"samples":{"normal":5,"urf":42},"wins":{"normal":2,"urf":18}},"fighter":{"samples":{"normal":18,"urf":57},"wins":{"normal":3,"urf":25}},"tank":{"samples":{"normal":6,"urf":35},"wins":{"normal":2,"urf":10}},"support":{"samples":{"normal":19,"urf":5},"wins":{"normal":1,"urf":2}}}},"Yorick":{"id":83,"key":"Yorick","name":"Yorick","title":"the Gravedigger","stats":{"total":{"samples":{"normal":774,"urf":1775},"wins":{"normal":366,"urf":880}},"ad":{"samples":{"normal":11,"urf":284},"wins":{"normal":5,"urf":148}},"ap":{"samples":{"normal":5,"urf":111},"wins":{"normal":2,"urf":53}},"fighter":{"samples":{"normal":105,"urf":287},"wins":{"normal":41,"urf":131}},"tank":{"samples":{"normal":602,"urf":1086},"wins":{"normal":299,"urf":544}},"support":{"samples":{"normal":51,"urf":7},"wins":{"normal":19,"urf":4}}}},"Urgot":{"id":6,"key":"Urgot","name":"Urgot","title":"the Headsman's Pride","stats":{"total":{"samples":{"normal":2229,"urf":3247},"wins":{"normal":1054,"urf":1633}},"ad":{"samples":{"normal":86,"urf":1116},"wins":{"normal":40,"urf":558}},"ap":{"samples":{"normal":3,"urf":35},"wins":{"normal":0,"urf":20}},"fighter":{"samples":{"normal":1833,"urf":1841},"wins":{"normal":883,"urf":915}},"tank":{"samples":{"normal":272,"urf":247},"wins":{"normal":117,"urf":136}},"support":{"samples":{"normal":35,"urf":8},"wins":{"normal":14,"urf":4}}}},"MissFortune":{"id":21,"key":"MissFortune","name":"Miss Fortune","title":"the Bounty Hunter","stats":{"total":{"samples":{"normal":2614,"urf":2149},"wins":{"normal":1313,"urf":963}},"ad":{"samples":{"normal":2483,"urf":1370},"wins":{"normal":1253,"urf":639}},"ap":{"samples":{"normal":64,"urf":733},"wins":{"normal":31,"urf":302}},"fighter":{"samples":{"normal":41,"urf":21},"wins":{"normal":15,"urf":10}},"tank":{"samples":{"normal":12,"urf":23},"wins":{"normal":8,"urf":11}},"support":{"samples":{"normal":14,"urf":2},"wins":{"normal":6,"urf":1}}}},"MonkeyKing":{"id":62,"key":"MonkeyKing","name":"Wukong","title":"the Monkey King","stats":{"total":{"samples":{"normal":4658,"urf":10352},"wins":{"normal":2411,"urf":5775}},"ad":{"samples":{"normal":31,"urf":1457},"wins":{"normal":18,"urf":862}},"ap":{"samples":{"normal":4,"urf":51},"wins":{"normal":1,"urf":22}},"fighter":{"samples":{"normal":3881,"urf":8067},"wins":{"normal":2033,"urf":4524}},"tank":{"samples":{"normal":717,"urf":769},"wins":{"normal":346,"urf":363}},"support":{"samples":{"normal":25,"urf":8},"wins":{"normal":13,"urf":4}}}},"Blitzcrank":{"id":53,"key":"Blitzcrank","name":"Blitzcrank","title":"the Great Steam Golem","stats":{"total":{"samples":{"normal":13395,"urf":16037},"wins":{"normal":6964,"urf":7912}},"ad":{"samples":{"normal":35,"urf":506},"wins":{"normal":17,"urf":261}},"ap":{"samples":{"normal":756,"urf":12500},"wins":{"normal":393,"urf":6225}},"fighter":{"samples":{"normal":52,"urf":202},"wins":{"normal":23,"urf":103}},"tank":{"samples":{"normal":599,"urf":1954},"wins":{"normal":302,"urf":934}},"support":{"samples":{"normal":11953,"urf":875},"wins":{"normal":6229,"urf":389}}}},"Shen":{"id":98,"key":"Shen","name":"Shen","title":"Eye of Twilight","stats":{"total":{"samples":{"normal":2932,"urf":3273},"wins":{"normal":1437,"urf":1748}},"ad":{"samples":{"normal":11,"urf":43},"wins":{"normal":5,"urf":31}},"ap":{"samples":{"normal":59,"urf":1249},"wins":{"normal":27,"urf":652}},"fighter":{"samples":{"normal":23,"urf":49},"wins":{"normal":15,"urf":22}},"tank":{"samples":{"normal":2657,"urf":1918},"wins":{"normal":1312,"urf":1040}},"support":{"samples":{"normal":182,"urf":14},"wins":{"normal":78,"urf":3}}}},"Braum":{"id":201,"key":"Braum","name":"Braum","title":"the Heart of the Freljord","stats":{"total":{"samples":{"normal":4224,"urf":837},"wins":{"normal":2185,"urf":410}},"ad":{"samples":{"normal":19,"urf":47},"wins":{"normal":7,"urf":32}},"ap":{"samples":{"normal":5,"urf":31},"wins":{"normal":1,"urf":13}},"fighter":{"samples":{"normal":16,"urf":47},"wins":{"normal":6,"urf":23}},"tank":{"samples":{"normal":279,"urf":550},"wins":{"normal":143,"urf":261}},"support":{"samples":{"normal":3905,"urf":162},"wins":{"normal":2028,"urf":81}}}},"XinZhao":{"id":5,"key":"XinZhao","name":"Xin Zhao","title":"the Seneschal of Demacia","stats":{"total":{"samples":{"normal":4842,"urf":7159},"wins":{"normal":2475,"urf":3881}},"ad":{"samples":{"normal":297,"urf":1725},"wins":{"normal":179,"urf":1015}},"ap":{"samples":{"normal":157,"urf":1613},"wins":{"normal":76,"urf":885}},"fighter":{"samples":{"normal":2067,"urf":1811},"wins":{"normal":1002,"urf":971}},"tank":{"samples":{"normal":2277,"urf":2008},"wins":{"normal":1209,"urf":1010}},"support":{"samples":{"normal":44,"urf":2},"wins":{"normal":9,"urf":0}}}},"Twitch":{"id":29,"key":"Twitch","name":"Twitch","title":"the Plague Rat","stats":{"total":{"samples":{"normal":3520,"urf":2294},"wins":{"normal":1590,"urf":1049}},"ad":{"samples":{"normal":3364,"urf":2207},"wins":{"normal":1547,"urf":1015}},"ap":{"samples":{"normal":6,"urf":33},"wins":{"normal":0,"urf":15}},"fighter":{"samples":{"normal":118,"urf":37},"wins":{"normal":36,"urf":14}},"tank":{"samples":{"normal":22,"urf":15},"wins":{"normal":5,"urf":4}},"support":{"samples":{"normal":10,"urf":2},"wins":{"normal":2,"urf":1}}}},"MasterYi":{"id":11,"key":"MasterYi","name":"Master Yi","title":"the Wuju Bladesman","stats":{"total":{"samples":{"normal":4951,"urf":12850},"wins":{"normal":2483,"urf":6854}},"ad":{"samples":{"normal":3184,"urf":11246},"wins":{"normal":1647,"urf":6106}},"ap":{"samples":{"normal":5,"urf":22},"wins":{"normal":2,"urf":11}},"fighter":{"samples":{"normal":1494,"urf":1475},"wins":{"normal":699,"urf":691}},"tank":{"samples":{"normal":259,"urf":93},"wins":{"normal":133,"urf":43}},"support":{"samples":{"normal":9,"urf":14},"wins":{"normal":2,"urf":3}}}},"Taric":{"id":44,"key":"Taric","name":"Taric","title":"the Gem Knight","stats":{"total":{"samples":{"normal":1479,"urf":1453},"wins":{"normal":781,"urf":682}},"ad":{"samples":{"normal":3,"urf":19},"wins":{"normal":0,"urf":11}},"ap":{"samples":{"normal":19,"urf":430},"wins":{"normal":9,"urf":195}},"fighter":{"samples":{"normal":6,"urf":24},"wins":{"normal":3,"urf":12}},"tank":{"samples":{"normal":289,"urf":854},"wins":{"normal":149,"urf":409}},"support":{"samples":{"normal":1162,"urf":126},"wins":{"normal":620,"urf":55}}}},"Amumu":{"id":32,"key":"Amumu","name":"Amumu","title":"the Sad Mummy","stats":{"total":{"samples":{"normal":6617,"urf":5502},"wins":{"normal":3502,"urf":2802}},"ad":{"samples":{"normal":0,"urf":13},"wins":{"normal":0,"urf":9}},"ap":{"samples":{"normal":762,"urf":4372},"wins":{"normal":452,"urf":2270}},"fighter":{"samples":{"normal":3,"urf":11},"wins":{"normal":1,"urf":2}},"tank":{"samples":{"normal":5738,"urf":1067},"wins":{"normal":3005,"urf":500}},"support":{"samples":{"normal":114,"urf":39},"wins":{"normal":44,"urf":21}}}},"Gangplank":{"id":41,"key":"Gangplank","name":"Gangplank","title":"the Saltwater Scourge","stats":{"total":{"samples":{"normal":2685,"urf":7248},"wins":{"normal":1350,"urf":3609}},"ad":{"samples":{"normal":1589,"urf":5868},"wins":{"normal":845,"urf":2975}},"ap":{"samples":{"normal":46,"urf":910},"wins":{"normal":28,"urf":425}},"fighter":{"samples":{"normal":236,"urf":234},"wins":{"normal":108,"urf":103}},"tank":{"samples":{"normal":724,"urf":229},"wins":{"normal":332,"urf":102}},"support":{"samples":{"normal":90,"urf":7},"wins":{"normal":37,"urf":4}}}},"Trundle":{"id":48,"key":"Trundle","name":"Trundle","title":"the Troll King","stats":{"total":{"samples":{"normal":2644,"urf":1222},"wins":{"normal":1282,"urf":605}},"ad":{"samples":{"normal":127,"urf":143},"wins":{"normal":42,"urf":77}},"ap":{"samples":{"normal":6,"urf":13},"wins":{"normal":1,"urf":2}},"fighter":{"samples":{"normal":742,"urf":555},"wins":{"normal":370,"urf":276}},"tank":{"samples":{"normal":1741,"urf":503},"wins":{"normal":858,"urf":248}},"support":{"samples":{"normal":28,"urf":8},"wins":{"normal":11,"urf":2}}}},"Kassadin":{"id":38,"key":"Kassadin","name":"Kassadin","title":"the Void Walker","stats":{"total":{"samples":{"normal":1658,"urf":5117},"wins":{"normal":723,"urf":2483}},"ad":{"samples":{"normal":5,"urf":39},"wins":{"normal":2,"urf":19}},"ap":{"samples":{"normal":1609,"urf":5019},"wins":{"normal":707,"urf":2439}},"fighter":{"samples":{"normal":7,"urf":11},"wins":{"normal":3,"urf":6}},"tank":{"samples":{"normal":28,"urf":40},"wins":{"normal":10,"urf":17}},"support":{"samples":{"normal":9,"urf":8},"wins":{"normal":1,"urf":2}}}},"Velkoz":{"id":161,"key":"Velkoz","name":"Vel'Koz","title":"the Eye of the Void","stats":{"total":{"samples":{"normal":2976,"urf":4820},"wins":{"normal":1517,"urf":2134}},"ad":{"samples":{"normal":3,"urf":23},"wins":{"normal":1,"urf":8}},"ap":{"samples":{"normal":2673,"urf":4772},"wins":{"normal":1387,"urf":2116}},"fighter":{"samples":{"normal":3,"urf":1},"wins":{"normal":1,"urf":0}},"tank":{"samples":{"normal":8,"urf":20},"wins":{"normal":3,"urf":9}},"support":{"samples":{"normal":289,"urf":4},"wins":{"normal":125,"urf":1}}}},"Zyra":{"id":143,"key":"Zyra","name":"Zyra","title":"Rise of the Thorns","stats":{"total":{"samples":{"normal":1988,"urf":3200},"wins":{"normal":1000,"urf":1609}},"ad":{"samples":{"normal":2,"urf":8},"wins":{"normal":0,"urf":5}},"ap":{"samples":{"normal":1595,"urf":3170},"wins":{"normal":855,"urf":1592}},"fighter":{"samples":{"normal":0,"urf":1},"wins":{"normal":0,"urf":1}},"tank":{"samples":{"normal":5,"urf":16},"wins":{"normal":1,"urf":9}},"support":{"samples":{"normal":386,"urf":5},"wins":{"normal":144,"urf":2}}}},"Nami":{"id":267,"key":"Nami","name":"Nami","title":"the Tidecaller","stats":{"total":{"samples":{"normal":5801,"urf":3823},"wins":{"normal":2948,"urf":1896}},"ad":{"samples":{"normal":18,"urf":26},"wins":{"normal":7,"urf":13}},"ap":{"samples":{"normal":598,"urf":3612},"wins":{"normal":337,"urf":1815}},"fighter":{"samples":{"normal":1,"urf":1},"wins":{"normal":1,"urf":0}},"tank":{"samples":{"normal":54,"urf":85},"wins":{"normal":29,"urf":31}},"support":{"samples":{"normal":5130,"urf":99},"wins":{"normal":2574,"urf":37}}}},"JarvanIV":{"id":59,"key":"JarvanIV","name":"Jarvan IV","title":"the Exemplar of Demacia","stats":{"total":{"samples":{"normal":6344,"urf":1810},"wins":{"normal":3032,"urf":911}},"ad":{"samples":{"normal":45,"urf":212},"wins":{"normal":24,"urf":112}},"ap":{"samples":{"normal":18,"urf":188},"wins":{"normal":5,"urf":82}},"fighter":{"samples":{"normal":4350,"urf":1220},"wins":{"normal":2118,"urf":629}},"tank":{"samples":{"normal":1766,"urf":187},"wins":{"normal":810,"urf":86}},"support":{"samples":{"normal":165,"urf":3},"wins":{"normal":75,"urf":2}}}},"Ezreal":{"id":81,"key":"Ezreal","name":"Ezreal","title":"the Prodigal Explorer","stats":{"total":{"samples":{"normal":10509,"urf":25299},"wins":{"normal":4897,"urf":12679}},"ad":{"samples":{"normal":4732,"urf":5864},"wins":{"normal":2399,"urf":2849}},"ap":{"samples":{"normal":1166,"urf":18864},"wins":{"normal":532,"urf":9586}},"fighter":{"samples":{"normal":1023,"urf":100},"wins":{"normal":387,"urf":50}},"tank":{"samples":{"normal":3517,"urf":465},"wins":{"normal":1559,"urf":194}},"support":{"samples":{"normal":71,"urf":6},"wins":{"normal":20,"urf":0}}}}}